{
  "operationId": "GetPaymenttransaction",
  "method": "GET",
  "path": "/api/oms/pvt/orders/{orderId}/payment-transaction",
  "summary": "VTex Retrieve payment transaction",
  "requestExamples": [],
  "responseExamples": [
    {
      "status": "200",
      "contentType": "application/json",
      "example": {
        "status": "Finished",
        "isActive": true,
        "transactionId": "CB452D77E7D04099A4DB0479087B1D2C",
        "merchantName": "LUXSTORE",
        "payments": [
          {
            "id": "721CBE1090324D12ABE301FE33DE775A",
            "paymentSystem": "4",
            "paymentSystemName": "Mastercard",
            "value": 10150,
            "installments": 1,
            "referenceValue": 10150,
            "cardHolder": null,
            "cardNumber": null,
            "firstDigits": "412341",
            "lastDigits": "4123",
            "url": null,
            "giftCardId": null,
            "giftCardName": null,
            "cvv2": null,
            "expireMonth": null,
            "expireYear": null,
            "giftCardCaption": null,
            "redemptionCode": null,
            "group": "creditCard",
            "tid": "101770752",
            "dueDate": null,
            "connectorResponses": {
              "Tid": "101770752",
              "ReturnCode": "200",
              "Message": "logMessage",
              "authId": "170852"
            }
          }
        ]
      }
    }
  ]
}