{
  "operationId": "EditReview",
  "method": "PATCH",
  "path": "/reviews-and-ratings/api/review/{reviewId}",
  "summary": "VTex Update a review",
  "requestExamples": [],
  "responseExamples": [
    {
      "status": "200",
      "contentType": "application/json",
      "example": {
        "id": "5323fdaa-c012-11ec-835d-0ebee58edbb3",
        "productId": "1",
        "rating": 5,
        "title": "Great product",
        "text": "Great product.",
        "reviewerName": "Arturo",
        "shopperId": "user@email.com",
        "reviewDateTime": "04/19/2022 18:55:58",
        "searchDate": "2022-04-19T18:55:58Z",
        "verifiedPurchaser": false,
        "sku": "2",
        "approved": false,
        "location": null,
        "locale": "en-US",
        "pastReviews": null
      }
    }
  ]
}